[{"name":"Bitcoin","id":"bitcoin","symbol":"btc","url":"https://api.coingecko.com/api/v3/coins/bitcoin"},{"name":"Ethereum","id":"ethereum","symbol":"eth","url":"https://api.coingecko.com/api/v3/coins/ethereum"},{"name":"Tether","id":"tether","symbol":"usdt","url":"https://api.coingecko.com/api/v3/coins/tether"},{"name":"BNB","id":"binancecoin","symbol":"bnb","url":"https://api.coingecko.com/api/v3/coins/binancecoin"},{"name":"USD Coin","id":"usd-coin","symbol":"usdc","url":"https://api.coingecko.com/api/v3/coins/usd-coin"},{"name":"Solana","id":"solana","symbol":"sol","url":"https://api.coingecko.com/api/v3/coins/solana"},{"name":"XRP","id":"ripple","symbol":"xrp","url":"https://api.coingecko.com/api/v3/coins/ripple"},{"name":"Terra","id":"terra-luna","symbol":"luna","url":"https://api.coingecko.com/api/v3/coins/terra-luna"},{"name":"Cardano","id":"cardano","symbol":"ada","url":"https://api.coingecko.com/api/v3/coins/cardano"},{"name":"Dogecoin","id":"dogecoin","symbol":"doge","url":"https://api.coingecko.com/api/v3/coins/dogecoin"}]